optirustic-0.4.1.dist-info/METADATA
optirustic-0.4.1.dist-info/WHEEL
optirustic/__init__.py
optirustic/__init__.pyi
optirustic/py.typed
optirustic/optirustic.cpython-39-darwin.so
optirustic-0.4.1.dist-info/RECORD
