Metadata-Version: 2.4
Name: optirustic
Version: 0.4.1
Classifier: Programming Language :: Rust
Classifier: Programming Language :: Python :: Implementation :: CPython
Classifier: Programming Language :: Python :: Implementation :: PyPy
Requires-Dist: matplotlib~=3.9.2
Requires-Dist: numpy~=2.0.1
Requires-Dist: ruff ; extra == 'dev'
Requires-Dist: maturin ; extra == 'dev'
Requires-Dist: pytest ; extra == 'dev'
Provides-Extra: dev
Requires-Python: >=3.8
